oh_llama/__init__.py
oh_llama-0.0.1.dist-info/METADATA
oh_llama-0.0.1.dist-info/WHEEL
oh_llama-0.0.1.dist-info/top_level.txt
oh_llama-0.0.1.dist-info/RECORD
