Metadata-Version: 2.1
Name: oh_llama
Version: 0.0.1
Summary: Opinionated, Ollama Client based Python Tools.
Author: Hammad Saeed
Author-email: hammad@supportvectors.com
Classifier: Programming Language :: Python :: 3
Classifier: License :: OSI Approved :: MIT License
Classifier: Operating System :: OS Independent
Requires-Python: >3.8
